[
  {
    "environment": "prod",
    "snapshots": [
      {
        "timestamp": 349,
        "candsInfo": [
          {
            "candidate": "1",
            "jobCount": 500
          },
          {
            "candidate": "2",
            "jobCount": 500
          },
          {
            "candidate": "3",
            "jobCount": 500
          },
          {
            "candidate": "4",
            "jobCount": 500
          }
        ]
      },
      {
        "timestamp": 745,
        "candsInfo": [
          {
            "candidate": "1",
            "jobCount": 667
          },
          {
            "candidate": "2",
            "jobCount": 667
          },
          {
            "candidate": "4",
            "jobCount": 666
          }
        ]
      }
    ]
  }
]
